pylitejet/__init__.py
pylitejet/_version.py
pylitejet-0.6.2.dist-info/LICENSE
pylitejet-0.6.2.dist-info/METADATA
pylitejet-0.6.2.dist-info/WHEEL
pylitejet-0.6.2.dist-info/top_level.txt
pylitejet-0.6.2.dist-info/RECORD
