Metadata-Version: 2.1
Name: pylitejet
Version: 0.6.2
Summary: A library for controlling a LiteJet lighting system.
Author-email: Jon Caruana <jon@joncaruana.com>
License: MIT License
Project-URL: repository, https://github.com/joncar/pylitejet.git
Keywords: litejet
Requires-Python: >=3.10
License-File: LICENSE
Requires-Dist: pyserial
